MANIFEST.in
README.rst
requirements.txt
setup.py
bin/reloadconf
reloadconf/__init__.py
reloadconf/__main__.py
reloadconf/version.py
reloadconf.egg-info/PKG-INFO
reloadconf.egg-info/SOURCES.txt
reloadconf.egg-info/dependency_links.txt
reloadconf.egg-info/not-zip-safe
reloadconf.egg-info/requires.txt
reloadconf.egg-info/top_level.txt