Metadata-Version: 1.1
Name: reloadconf
Version: 1.1.15
Summary: Simple process manager
Home-page: https://github.com/btimby/reloadconf/
Author: Ben Timby
Author-email: btimby@smartfile.com
License: UNKNOWN
Platform: UNKNOWN
Classifier: Development Status :: 4 - Beta
Classifier: Environment :: Web Environment
Classifier: Intended Audience :: Developers
Classifier: Operating System :: OS Independent
Classifier: Programming Language :: Python
Classifier: Framework :: Django
